{
  "generated": "2026-04-07T02:46:23.736099",
  "window_days": 28,
  "count": 16,
  "meetings": [
    {
      "body": "Planning Commission",
      "date": "2026-04-06",
      "time": "6:00 PM",
      "location": "City of Phoenix (see notice PDF for location/virtual link)",
      "virtual_url": "",
      "agenda_url": "https://www.phoenix.gov/content/dam/phoenix/cityclerksite/publicmeetings/notices/2026/april/260406004.pdf",
      "source_label": "City of Phoenix",
      "relevant_items": [
        {
          "title": "NOTICE OF PUBLIC HEARING",
          "matched_keywords": [
            "public hearing"
          ]
        },
        {
          "title": "48-hour period. Due to the added demands of facilitating the virtual environment for the",
          "matched_keywords": [
            "environment"
          ]
        },
        {
          "title": "Rezoning and text amendment staff reports, addendums, and staff memos are available",
          "matched_keywords": [
            "rezoning"
          ]
        },
        {
          "title": "zoning/pzservices/pzstaff-reports.",
          "matched_keywords": [
            "zoning"
          ]
        },
        {
          "title": "PUD rezoning staff reports, narratives, addendums, and staff memos are available here:",
          "matched_keywords": [
            "rezoning"
          ]
        },
        {
          "title": "https://www.phoenix.gov/pdd/planning-zoning/pzservices/pud-cases.",
          "matched_keywords": [
            "zoning"
          ]
        },
        {
          "title": "Proposal: Minor General Plan Amendment to accommodate",
          "matched_keywords": [
            "general plan"
          ]
        },
        {
          "title": "Applicant: John Buckel, MP Environmental Services, Inc.",
          "matched_keywords": [
            "environmental"
          ]
        },
        {
          "title": "REZONING CASES",
          "matched_keywords": [
            "rezoning"
          ]
        },
        {
          "title": "Proposal: Historic Preservation Zoning Overlay for E.H. Coe",
          "matched_keywords": [
            "zoning"
          ]
        },
        {
          "title": "If appealed, the City Council public hearing will be held on May 6, 2026 at 2:30 p.m. If",
          "matched_keywords": [
            "public hearing"
          ]
        }
      ],
      "notes": ""
    },
    {
      "body": "Planning Commission Briefing",
      "date": "2026-04-06",
      "time": "4:30 PM",
      "location": "City of Phoenix (see notice PDF for location/virtual link)",
      "virtual_url": "",
      "agenda_url": "https://www.phoenix.gov/content/dam/phoenix/cityclerksite/publicmeetings/notices/2026/april/260406005.pdf",
      "source_label": "City of Phoenix",
      "relevant_items": [
        {
          "title": "A. Presentation and discussion regarding updates on the General Plan Next",
          "matched_keywords": [
            "general plan"
          ]
        },
        {
          "title": "(Rio Salado District) Policy Plan and initiation of a new General Plan",
          "matched_keywords": [
            "general plan"
          ]
        },
        {
          "title": "B. Presentation, discussion, and possible initiation of a General Plan",
          "matched_keywords": [
            "general plan"
          ]
        },
        {
          "title": "Amendment of the General Plan Land Use Map to be in alignment with the",
          "matched_keywords": [
            "general plan",
            "land use"
          ]
        },
        {
          "title": "VI. TIME ALLOCATION FOR PUBLIC HEARING ITEMS ON THE EVENING",
          "matched_keywords": [
            "public hearing"
          ]
        }
      ],
      "notes": ""
    },
    {
      "body": "MAG Transportation Safety Committee",
      "date": "2026-04-07",
      "time": "See agenda",
      "location": "302 N. 1st Ave, Suite 300, Phoenix AZ 85003 (hybrid)",
      "virtual_url": "https://azmag.gov/About-Us/Calendar",
      "agenda_url": "https://azmag.gov/Portals/0/Committee-Meetings/2026/TSC/TSC-2026-04-07-Agenda.pdf",
      "source_label": "MAG",
      "relevant_items": [],
      "notes": "Estimated meeting date based on typical MAG Transportation Safety Committee schedule. Confirm at azmag.gov/About-Us/Calendar. Agenda PDF (if posted): https://azmag.gov/Portals/0/Committee-Meetings/2026/TSC/TSC-2026-04-07-Agenda.pdf"
    },
    {
      "body": "Board of Supervisors - Planning and Zoning Agenda Items",
      "date": "2026-04-08",
      "time": "9:00 AM",
      "location": "301 W. Jefferson St., Phoenix AZ 85003",
      "virtual_url": "https://www.maricopa.gov/324",
      "agenda_url": "https://www.maricopa.gov/AgendaCenter/ViewFile/Agenda/_04082026-3706?html=true",
      "source_label": "Maricopa County",
      "relevant_items": [],
      "notes": ""
    },
    {
      "body": "City Council Formal Meeting",
      "date": "2026-04-08",
      "time": "2:30 PM",
      "location": "phoenix.gov",
      "virtual_url": "",
      "agenda_url": "https://www.phoenix.gov/content/dam/phoenix/cityclerksite/publicmeetings/notices/2026/april/260408001.pdf",
      "source_label": "City of Phoenix",
      "relevant_items": [
        {
          "title": "Item 1: City Council Formal Meeting Agenda April 8, 2026",
          "matched_keywords": []
        },
        {
          "title": "Item 1: Mayor and Council Appointments to Boards and",
          "matched_keywords": []
        },
        {
          "title": "Item 2: Liquor License - Lupe - District 4",
          "matched_keywords": []
        },
        {
          "title": "Item 3: Liquor License - Turney Neighborhood Market - District 4",
          "matched_keywords": []
        },
        {
          "title": "Item 4: Liquor License - Special Event - Pathway to Work -",
          "matched_keywords": []
        },
        {
          "title": "Item 5: Liquor License - Special Event - St. Theresa Council No",
          "matched_keywords": []
        },
        {
          "title": "Item 6: Liquor License - Cheba Hut Toasted Subs - District 6",
          "matched_keywords": []
        },
        {
          "title": "Item 7: Liquor License - Shake Shack #1771 - District 6",
          "matched_keywords": []
        },
        {
          "title": "Item 8: Liquor License - Buckeye Market - District 7",
          "matched_keywords": []
        },
        {
          "title": "Item 9: Liquor License - Oro De Sonora - District 7",
          "matched_keywords": []
        },
        {
          "title": "Item 10: Liquor License - Lynx Distribution - District 8",
          "matched_keywords": []
        },
        {
          "title": "Item 11: Liquor License - Tacos Del Pepe 2 LLC - District 8",
          "matched_keywords": []
        },
        {
          "title": "Item 12: Liquor License - AN Smoke Shop - District 3",
          "matched_keywords": []
        },
        {
          "title": "Item 13: Applied Economics, LLC",
          "matched_keywords": []
        },
        {
          "title": "Item 14: Regina Munro dba Medic A&P, Inc.",
          "matched_keywords": []
        },
        {
          "title": "Item 15: Duncor, LLC dba Summit West Signs",
          "matched_keywords": []
        },
        {
          "title": "Item 16: When to Work, LLC",
          "matched_keywords": []
        },
        {
          "title": "Item 17: Phoenix Employment Relations Board (PERB) Hearing",
          "matched_keywords": []
        },
        {
          "title": "Item 18: Settlement of Claim(s) Mangan v. City of Phoenix",
          "matched_keywords": []
        },
        {
          "title": "Item 19: Landscape Sprinkler and Irrigation Supplies Contract -",
          "matched_keywords": []
        },
        {
          "title": "Item 20: Cloud Solutions CTR046098 - Amendment (Ordinance",
          "matched_keywords": []
        },
        {
          "title": "Item 21: Acceptance and Dedication of Easements for Public",
          "matched_keywords": []
        },
        {
          "title": "Item 22: Acceptance of Easements for Drainage Purposes",
          "matched_keywords": []
        },
        {
          "title": "Item 23: Part- Time Television Engineering Services Contract -",
          "matched_keywords": []
        },
        {
          "title": "Item 24: Amendments to the City's Combined Classification and",
          "matched_keywords": []
        },
        {
          "title": "Item 25: Authorization to Enter Into Contract with Father Matters,",
          "matched_keywords": []
        },
        {
          "title": "Item 26: Retroactive Authorization to Apply for, Accept and",
          "matched_keywords": []
        },
        {
          "title": "Item 27: NFL FLAG Youth League Equipment and Apparel -",
          "matched_keywords": []
        },
        {
          "title": "Item 28: Event Equipment Rental Services - PKS-IFB-26-0175 (Ordinance",
          "matched_keywords": []
        },
        {
          "title": "Item 29: Lifeguard Uniforms Contract - PKS-IFB-26-0193 Request",
          "matched_keywords": []
        }
      ],
      "notes": ""
    },
    {
      "body": "Economic Development and the Arts Subcommittee",
      "date": "2026-04-08",
      "time": "10:00 AM",
      "location": "City Council Chambers",
      "virtual_url": "",
      "agenda_url": "https://www.phoenix.gov/content/dam/phoenix/cityclerksite/publicmeetings/notices/2026/april/260408002.pdf",
      "source_label": "City of Phoenix",
      "relevant_items": [
        {
          "title": "Item 1: Economic Development and Agenda April 8, 2026",
          "matched_keywords": []
        },
        {
          "title": "Item 1: Minutes of the Economic Development and the Arts",
          "matched_keywords": []
        },
        {
          "title": "Item 2: Arizona Department of Economic Security",
          "matched_keywords": []
        },
        {
          "title": "Item 3: Downtown Phoenix Entertainment District",
          "matched_keywords": []
        },
        {
          "title": "Item 4: Upcoming Events and Programs at Cultural",
          "matched_keywords": []
        },
        {
          "title": "Item 5: Phoenix Economic Overview and Update: Part 3 - Land,",
          "matched_keywords": []
        },
        {
          "title": "Item 5: Economic Development and the Arts Subcommittee",
          "matched_keywords": []
        }
      ],
      "notes": ""
    },
    {
      "body": "MAG Management Committee",
      "date": "2026-04-08",
      "time": "See agenda",
      "location": "302 N. 1st Ave, Suite 300, Phoenix AZ 85003 (hybrid)",
      "virtual_url": "https://azmag.gov/About-Us/Calendar",
      "agenda_url": "https://azmag.gov/Portals/0/Committee-Meetings/2026/MC/MC-2026-04-08-Agenda.pdf",
      "source_label": "MAG",
      "relevant_items": [],
      "notes": "Estimated meeting date based on typical MAG Management Committee schedule. Confirm at azmag.gov/About-Us/Calendar. Agenda PDF (if posted): https://azmag.gov/Portals/0/Committee-Meetings/2026/MC/MC-2026-04-08-Agenda.pdf"
    },
    {
      "body": "MAG Environment & Sustainable Communities",
      "date": "2026-04-09",
      "time": "See agenda",
      "location": "302 N. 1st Ave, Suite 300, Phoenix AZ 85003 (hybrid)",
      "virtual_url": "https://azmag.gov/About-Us/Calendar",
      "agenda_url": "https://azmag.gov/Portals/0/Committee-Meetings/2026/ESCC/ESCC-2026-04-09-Agenda.pdf",
      "source_label": "MAG",
      "relevant_items": [],
      "notes": "Estimated meeting date based on typical MAG Environment & Sustainable Communities schedule. Confirm at azmag.gov/About-Us/Calendar. Agenda PDF (if posted): https://azmag.gov/Portals/0/Committee-Meetings/2026/ESCC/ESCC-2026-04-09-Agenda.pdf"
    },
    {
      "body": "Planning and Zoning Commission Meeting - BOS Auditorium & GoTo Webinar",
      "date": "2026-04-09",
      "time": "9:00 AM",
      "location": "301 W. Jefferson St., Phoenix AZ 85003",
      "virtual_url": "https://www.maricopa.gov/324 (see agenda for GoToWebinar access code)",
      "agenda_url": "https://www.maricopa.gov/AgendaCenter/ViewFile/Agenda/_04092026-3711?html=true",
      "source_label": "Maricopa County",
      "relevant_items": [],
      "notes": ""
    },
    {
      "body": "MAG Transportation Policy Committee",
      "date": "2026-04-15",
      "time": "See agenda",
      "location": "302 N. 1st Ave, Suite 300, Phoenix AZ 85003 (hybrid)",
      "virtual_url": "https://azmag.gov/About-Us/Calendar",
      "agenda_url": "https://azmag.gov/Portals/0/Committee-Meetings/2026/TPC/TPC-2026-04-15-Agenda.pdf",
      "source_label": "MAG",
      "relevant_items": [],
      "notes": "Estimated meeting date based on typical MAG Transportation Policy Committee schedule. Confirm at azmag.gov/About-Us/Calendar. Agenda PDF (if posted): https://azmag.gov/Portals/0/Committee-Meetings/2026/TPC/TPC-2026-04-15-Agenda.pdf"
    },
    {
      "body": "MAG Human Services & Public Safety Committee",
      "date": "2026-04-16",
      "time": "See agenda",
      "location": "302 N. 1st Ave, Suite 300, Phoenix AZ 85003 (hybrid)",
      "virtual_url": "https://azmag.gov/About-Us/Calendar",
      "agenda_url": "https://azmag.gov/Portals/0/Committee-Meetings/2026/HSPS/HSPS-2026-04-16-Agenda.pdf",
      "source_label": "MAG",
      "relevant_items": [],
      "notes": "Estimated meeting date based on typical MAG Human Services & Public Safety Committee schedule. Confirm at azmag.gov/About-Us/Calendar. Agenda PDF (if posted): https://azmag.gov/Portals/0/Committee-Meetings/2026/HSPS/HSPS-2026-04-16-Agenda.pdf"
    },
    {
      "body": "MAG Active Transportation Committee",
      "date": "2026-04-21",
      "time": "See agenda",
      "location": "302 N. 1st Ave, Suite 300, Phoenix AZ 85003 (hybrid)",
      "virtual_url": "https://azmag.gov/About-Us/Calendar",
      "agenda_url": "https://azmag.gov/Portals/0/Committee-Meetings/2026/ATC/ATC-2026-04-21-Agenda.pdf",
      "source_label": "MAG",
      "relevant_items": [],
      "notes": "Estimated meeting date based on typical MAG Active Transportation Committee schedule. Confirm at azmag.gov/About-Us/Calendar. Agenda PDF (if posted): https://azmag.gov/Portals/0/Committee-Meetings/2026/ATC/ATC-2026-04-21-Agenda.pdf"
    },
    {
      "body": "MAG Regional Council",
      "date": "2026-04-22",
      "time": "See agenda",
      "location": "302 N. 1st Ave, Suite 300, Phoenix AZ 85003 (hybrid)",
      "virtual_url": "https://azmag.gov/About-Us/Calendar",
      "agenda_url": "https://azmag.gov/Portals/0/Committee-Meetings/2026/RC/RC-2026-04-22-Agenda.pdf",
      "source_label": "MAG",
      "relevant_items": [],
      "notes": "Estimated meeting date based on typical MAG Regional Council schedule. Confirm at azmag.gov/About-Us/Calendar. Agenda PDF (if posted): https://azmag.gov/Portals/0/Committee-Meetings/2026/RC/RC-2026-04-22-Agenda.pdf"
    },
    {
      "body": "Valley Metro Board of Directors (RPTA & VMR)",
      "date": "2026-04-23",
      "time": "~11:15 AM (estimate \u2014 verify)",
      "location": "101 N. 1st Ave, Suite 1400, Phoenix AZ 85003",
      "virtual_url": "https://www.valleymetro.org/event/valley-metro-board-meetings",
      "agenda_url": "https://www.valleymetro.org/about/boards-directors/board-book",
      "source_label": "Valley Metro",
      "relevant_items": [],
      "notes": "Valley Metro's website requires a manual check for confirmed dates and agenda. Visit valleymetro.org/about/boards-directors/board-book \u2014 boards typically meet on the third Thursday of each month."
    },
    {
      "body": "MAG Regional Council Executive Committee",
      "date": "2026-05-04",
      "time": "See agenda",
      "location": "302 N. 1st Ave, Suite 300, Phoenix AZ 85003 (hybrid)",
      "virtual_url": "https://azmag.gov/About-Us/Calendar",
      "agenda_url": "https://azmag.gov/Portals/0/Committee-Meetings/2026/EC/EC-2026-05-04-Agenda.pdf",
      "source_label": "MAG",
      "relevant_items": [],
      "notes": "Estimated meeting date based on typical MAG Regional Council Executive Committee schedule. Confirm at azmag.gov/About-Us/Calendar. Agenda PDF (if posted): https://azmag.gov/Portals/0/Committee-Meetings/2026/EC/EC-2026-05-04-Agenda.pdf"
    },
    {
      "body": "MAG Transportation Safety Committee",
      "date": "2026-05-05",
      "time": "See agenda",
      "location": "302 N. 1st Ave, Suite 300, Phoenix AZ 85003 (hybrid)",
      "virtual_url": "https://azmag.gov/About-Us/Calendar",
      "agenda_url": "https://azmag.gov/Portals/0/Committee-Meetings/2026/TSC/TSC-2026-05-05-Agenda.pdf",
      "source_label": "MAG",
      "relevant_items": [],
      "notes": "Estimated meeting date based on typical MAG Transportation Safety Committee schedule. Confirm at azmag.gov/About-Us/Calendar. Agenda PDF (if posted): https://azmag.gov/Portals/0/Committee-Meetings/2026/TSC/TSC-2026-05-05-Agenda.pdf"
    }
  ]
}